geniusrise_huggingface/__init__.py
geniusrise_huggingface/base.py
geniusrise_huggingface/classification.py
geniusrise_huggingface/commonsense_reasoning.py
geniusrise_huggingface/embeddings.py
geniusrise_huggingface/instruction_tuning.py
geniusrise_huggingface/language_model.py
geniusrise_huggingface/ner.py
geniusrise_huggingface/question_answering.py
geniusrise_huggingface/sentiment_analysis.py
geniusrise_huggingface/summarization.py
geniusrise_huggingface/translation.py
geniusrise_huggingface-0.4.9.dist-info/METADATA
geniusrise_huggingface-0.4.9.dist-info/WHEEL
geniusrise_huggingface-0.4.9.dist-info/top_level.txt
geniusrise_huggingface-0.4.9.dist-info/RECORD
